{
  "spec_slug": "15.0-cargo-workspace-skeleton",
  "branch": "15.0-cargo-workspace-skeleton-flow",
  "started_at": "2026-07-02T21:52:55Z",
  "updated_at": "2026-07-02T22:40:28Z",
  "worktree_path": "/Users/brandon/Dev/agentic-portfolio/core/bastion/trees/15.0-cargo-workspace-skeleton-flow",
  "status": "done",
  "current_task": null,
  "tasks": {},
  "review": {
    "verdict": "PASS",
    "findings": [],
    "attempts": 1
  },
  "docs": {
    "changed": [],
    "created": []
  },
  "bail_reason": null,
  "pr": {
    "url": null,
    "number": null
  },
  "tokens": {
    "stages": [
      {
        "label": "worktree-setup",
        "model": "haiku",
        "promptTokEst": 1118,
        "filesReadKb": null,
        "inTokEst": 1118,
        "outTok": 2465
      },
      {
        "label": "enumerate",
        "model": "haiku",
        "promptTokEst": 259,
        "filesReadKb": null,
        "inTokEst": 259,
        "outTok": 588
      },
      {
        "label": "state-load",
        "model": "haiku",
        "promptTokEst": 232,
        "filesReadKb": null,
        "inTokEst": 232,
        "outTok": 930
      },
      {
        "label": "review-1",
        "model": "sonnet",
        "promptTokEst": 1022,
        "filesReadKb": null,
        "inTokEst": 1022,
        "outTok": 3105
      },
      {
        "label": "docs",
        "model": "sonnet",
        "promptTokEst": 830,
        "filesReadKb": null,
        "inTokEst": 830,
        "outTok": 3516
      },
      {
        "label": "wrap-up",
        "model": "sonnet",
        "promptTokEst": 862,
        "filesReadKb": null,
        "inTokEst": 862,
        "outTok": 2621
      }
    ],
    "total": {
      "promptTokEst": 4323,
      "filesReadKb": 0,
      "inTokEst": 4323,
      "outTok": 13225
    }
  }
}
